[
	{
		"title": "Pronites",
		"events": [
			{
				"name": "Amit Mishra",
				"image": "amit.png"
			},
			{
				"name": "Ravi Gupta",
				"image": "darshan_raval.png"
			},
			{
				"name": "Udan Khatola",
					"image": "darshan_raval.png"
			},
			{
				"name": "T. R. A. P.",
				"image": "trap.png"
			},
			{
				"name": "D.J. Oja",
				"image": "darshan_raval.png"
			}
		]
	},
	{
		"title": "Talks",
		"events": [
			{
				"name": "Prashanth Varma",
				"image": "darshan_raval.png"
			},
			{
				"name": "Kamal K. Kumawat",
				"image": "darshan_raval.png"
			}
		]
	}
]

